secsummarize/__init__.py
secsummarize/main.py
secsummarize/prompts.py
secsummarize-2025.12.20202849.dist-info/METADATA
secsummarize-2025.12.20202849.dist-info/WHEEL
secsummarize-2025.12.20202849.dist-info/top_level.txt
secsummarize-2025.12.20202849.dist-info/RECORD
