Metadata-Version: 2.4
Name: secsummarize
Version: 2025.12.20202849
Summary: This package processes user-provided text to generate structured summaries of security-related topics, such as incident reports or research findings, extracting key insights, vulnerabilities, and reco
Author-email: secsummarize <hi@eugene.plus>
License: MIT
Project-URL: Homepage, https://github.com/chigwell/secsummarize
Requires-Python: >=3.9
Requires-Dist: langchain-llm7>=0.0.0
Requires-Dist: llmatch-messages>=0.0.0
Requires-Dist: langchain-core>=0.3.0
